{"packages":{"pascalwoerde/coinmarketcap-api-client":{"v1.0.0-beta":{"name":"pascalwoerde/coinmarketcap-api-client","description":"PHP Client for the CoinMarketCap API","keywords":[],"homepage":"","version":"v1.0.0-beta","version_normalized":"1.0.0.0-beta","license":["MIT"],"authors":[],"source":{"type":"git","url":"https://github.com/pascalwoerde/coinmarketcap-api-client.git","reference":"13f784d69437402b0cc766d5ab59fa9b85f4aa71"},"dist":{"type":"zip","url":"https://api.github.com/repos/pascalwoerde/coinmarketcap-api-client/zipball/13f784d69437402b0cc766d5ab59fa9b85f4aa71","reference":"13f784d69437402b0cc766d5ab59fa9b85f4aa71","shasum":""},"type":"library","time":"2018-01-01T18:19:47+00:00","autoload":{"psr-4":{"PascalWoerde\\CoinMarketCap\\":"src/"}},"require":{"php":"^7.0.0","psr/http-message":"^1.0","php-http/httplug":"^1.1","php-http/message-factory":"^1.0","php-http/discovery":"^1.3"},"require-dev":{"phpunit/phpunit":"^6.5","php-http/mock-client":"^1.0","php-http/message":"^1.6","guzzlehttp/psr7":"^1.4"},"provide":{"php-http/guzzle6-adapter":"^1.1"},"uid":1819369}},"php-http/guzzle6-adapter":{"dev-master":{"name":"php-http/guzzle6-adapter","description":"Guzzle 6 HTTP Adapter","keywords":["http","Guzzle"],"homepage":"http://httplug.io","version":"dev-master","version_normalized":"9999999-dev","license":["MIT"],"authors":[{"name":"Márk Sági-Kazár","email":"mark.sagikazar@gmail.com"},{"name":"David de Boer","email":"david@ddeboer.nl"}],"source":{"type":"git","url":"https://github.com/php-http/guzzle6-adapter.git","reference":"4b491b78e1b24ca941e6ca925f48a63e6a2d9a45"},"dist":{"type":"zip","url":"https://api.github.com/repos/php-http/guzzle6-adapter/zipball/4b491b78e1b24ca941e6ca925f48a63e6a2d9a45","reference":"4b491b78e1b24ca941e6ca925f48a63e6a2d9a45","shasum":""},"type":"library","time":"2019-03-13T07:21:18+00:00","autoload":{"psr-4":{"Http\\Adapter\\Guzzle6\\":"src/"}},"extra":{"branch-alias":{"dev-master":"2.x-dev"}},"require":{"guzzlehttp/guzzle":"^6.0","php":"^7.1","php-http/httplug":"^2.0","psr/http-client":"^1.0"},"require-dev":{"ext-curl":"*","php-http/client-integration-tests":"^2.0","phpunit/phpunit":"^7.4"},"provide":{"php-http/client-implementation":"1.0","php-http/async-client-implementation":"1.0","psr/http-client-implementation":"1.0"},"uid":414147},"v0.1.0":{"name":"php-http/guzzle6-adapter","description":"Guzzle 6 HTTP adapter","keywords":["http","Guzzle"],"homepage":"http://php-http.org","version":"v0.1.0","version_normalized":"0.1.0.0","license":["MIT"],"authors":[{"name":"Márk Sági-Kazár","email":"mark.sagikazar@gmail.com"},{"name":"David de Boer","email":"david@ddeboer.nl"}],"source":{"type":"git","url":"https://github.com/php-http/guzzle6-adapter.git","reference":"a4ff6a8e9fe2e25f097727568d9eaea8b293faa7"},"dist":{"type":"zip","url":"https://api.github.com/repos/php-http/guzzle6-adapter/zipball/a4ff6a8e9fe2e25f097727568d9eaea8b293faa7","reference":"a4ff6a8e9fe2e25f097727568d9eaea8b293faa7","shasum":""},"type":"library","time":"2015-06-12T13:31:57+00:00","autoload":{"psr-4":{"Http\\Adapter\\":"src/"}},"extra":{"branch-alias":{"dev-master":"0.1-dev"}},"require":{"php":">=5.4","php-http/adapter":"^0.1","guzzlehttp/guzzle":"~6.0"},"require-dev":{"ext-curl":"*","php-http/adapter-integration-tests":"^0.1"},"provide":{"php-http/adapter-implementation":"0.1"},"uid":431952},"v0.2.0":{"name":"php-http/guzzle6-adapter","description":"Guzzle 6 HTTP Adapter","keywords":["http","Guzzle"],"homepage":"http://httplug.io","version":"v0.2.0","version_normalized":"0.2.0.0","license":["MIT"],"authors":[{"name":"Márk Sági-Kazár","email":"mark.sagikazar@gmail.com"},{"name":"David de Boer","email":"david@ddeboer.nl"}],"source":{"type":"git","url":"https://github.com/php-http/guzzle6-adapter.git","reference":"fd6971aa9bb68150af87c2da7d18730efcbe2bf4"},"dist":{"type":"zip","url":"https://api.github.com/repos/php-http/guzzle6-adapter/zipball/fd6971aa9bb68150af87c2da7d18730efcbe2bf4","reference":"fd6971aa9bb68150af87c2da7d18730efcbe2bf4","shasum":""},"type":"library","time":"2015-12-15T16:46:17+00:00","autoload":{"psr-4":{"Http\\Adapter\\":"src/"}},"extra":{"branch-alias":{"dev-master":"0.3-dev"}},"require":{"php":">=5.5.0","php-http/httplug":"1.0.0-alpha3","php-http/client-tools":"^0.1","guzzlehttp/guzzle":"^6.0"},"require-dev":{"ext-curl":"*","php-http/adapter-integration-tests":"dev-master"},"provide":{"php-http/client-implementation":"1.0","php-http/async-client-implementation":"1.0"},"uid":623634},"v0.2.1":{"name":"php-http/guzzle6-adapter","description":"Guzzle 6 HTTP Adapter","keywords":["http","Guzzle"],"homepage":"http://httplug.io","version":"v0.2.1","version_normalized":"0.2.1.0","license":["MIT"],"authors":[{"name":"Márk Sági-Kazár","email":"mark.sagikazar@gmail.com"},{"name":"David de Boer","email":"david@ddeboer.nl"}],"source":{"type":"git","url":"https://github.com/php-http/guzzle6-adapter.git","reference":"02f261e116a043f2df6992fc89cec2adbfb94ca5"},"dist":{"type":"zip","url":"https://api.github.com/repos/php-http/guzzle6-adapter/zipball/02f261e116a043f2df6992fc89cec2adbfb94ca5","reference":"02f261e116a043f2df6992fc89cec2adbfb94ca5","shasum":""},"type":"library","time":"2015-12-17T15:54:17+00:00","autoload":{"psr-4":{"Http\\Adapter\\":"src/"}},"extra":{"branch-alias":{"dev-master":"0.3-dev"}},"require":{"php":">=5.5.0","php-http/httplug":"1.0.0-beta","php-http/client-tools":"^0.1","guzzlehttp/guzzle":"^6.0"},"require-dev":{"ext-curl":"*","php-http/adapter-integration-tests":"dev-master"},"provide":{"php-http/client-implementation":"1.0","php-http/async-client-implementation":"1.0"},"uid":626407},"v0.3.0":{"name":"php-http/guzzle6-adapter","description":"Guzzle 6 HTTP Adapter","keywords":["http","Guzzle"],"homepage":"http://httplug.io","version":"v0.3.0","version_normalized":"0.3.0.0","license":["MIT"],"authors":[{"name":"Márk Sági-Kazár","email":"mark.sagikazar@gmail.com"},{"name":"David de Boer","email":"david@ddeboer.nl"}],"source":{"type":"git","url":"https://github.com/php-http/guzzle6-adapter.git","reference":"b2bfbe59f70a5e5771ce56b786fb600a093da100"},"dist":{"type":"zip","url":"https://api.github.com/repos/php-http/guzzle6-adapter/zipball/b2bfbe59f70a5e5771ce56b786fb600a093da100","reference":"b2bfbe59f70a5e5771ce56b786fb600a093da100","shasum":""},"type":"library","time":"2015-12-31T14:18:09+00:00","autoload":{"psr-4":{"Http\\Adapter\\Guzzle6\\":"src/"}},"extra":{"branch-alias":{"dev-master":"0.3-dev"}},"require":{"php":">=5.5.0","php-http/httplug":"1.0.0-beta","php-http/client-common":"^0.1","guzzlehttp/guzzle":"^6.0"},"require-dev":{"ext-curl":"*","php-http/adapter-integration-tests":"dev-master"},"provide":{"php-http/client-implementation":"1.0","php-http/async-client-implementation":"1.0"},"uid":640384},"v0.3.1":{"name":"php-http/guzzle6-adapter","description":"Guzzle 6 HTTP Adapter","keywords":["http","Guzzle"],"homepage":"http://httplug.io","version":"v0.3.1","version_normalized":"0.3.1.0","license":["MIT"],"authors":[{"name":"Márk Sági-Kazár","email":"mark.sagikazar@gmail.com"},{"name":"David de Boer","email":"david@ddeboer.nl"}],"source":{"type":"git","url":"https://github.com/php-http/guzzle6-adapter.git","reference":"9d729a740ebeae40d7984344e9fc7cc14943a3e5"},"dist":{"type":"zip","url":"https://api.github.com/repos/php-http/guzzle6-adapter/zipball/9d729a740ebeae40d7984344e9fc7cc14943a3e5","reference":"9d729a740ebeae40d7984344e9fc7cc14943a3e5","shasum":""},"type":"library","time":"2015-12-31T14:56:30+00:00","autoload":{"psr-4":{"Http\\Adapter\\Guzzle6\\":"src/"}},"extra":{"branch-alias":{"dev-master":"0.3-dev"}},"require":{"php":">=5.5.0","php-http/httplug":"1.0.0-beta","php-http/client-common":"^0.1","guzzlehttp/guzzle":"^6.0"},"require-dev":{"ext-curl":"*","php-http/adapter-integration-tests":"dev-master"},"provide":{"php-http/client-implementation":"1.0","php-http/async-client-implementation":"1.0"},"uid":640413},"v0.4.0":{"name":"php-http/guzzle6-adapter","description":"Guzzle 6 HTTP Adapter","keywords":["http","Guzzle"],"homepage":"http://httplug.io","version":"v0.4.0","version_normalized":"0.4.0.0","license":["MIT"],"authors":[{"name":"Márk Sági-Kazár","email":"mark.sagikazar@gmail.com"},{"name":"David de Boer","email":"david@ddeboer.nl"}],"source":{"type":"git","url":"https://github.com/php-http/guzzle6-adapter.git","reference":"306b113a19bf3329646bb6ed0035982981d4f0aa"},"dist":{"type":"zip","url":"https://api.github.com/repos/php-http/guzzle6-adapter/zipball/306b113a19bf3329646bb6ed0035982981d4f0aa","reference":"306b113a19bf3329646bb6ed0035982981d4f0aa","shasum":""},"type":"library","time":"2016-01-12T16:51:21+00:00","autoload":{"psr-4":{"Http\\Adapter\\Guzzle6\\":"src/"}},"extra":{"branch-alias":{"dev-master":"0.5-dev"}},"require":{"php":">=5.5.0","php-http/httplug":"^1.0","php-http/client-common":"^0.2","guzzlehttp/guzzle":"^6.0"},"require-dev":{"ext-curl":"*","php-http/adapter-integration-tests":"dev-master"},"provide":{"php-http/client-implementation":"1.0","php-http/async-client-implementation":"1.0"},"uid":654492},"v0.4.1":{"name":"php-http/guzzle6-adapter","description":"Guzzle 6 HTTP Adapter","keywords":["http","Guzzle"],"homepage":"http://httplug.io","version":"v0.4.1","version_normalized":"0.4.1.0","license":["MIT"],"authors":[{"name":"Márk Sági-Kazár","email":"mark.sagikazar@gmail.com"},{"name":"David de Boer","email":"david@ddeboer.nl"}],"source":{"type":"git","url":"https://github.com/php-http/guzzle6-adapter.git","reference":"459fa6e436cdc842bf3edf030dca7ecca9badec3"},"dist":{"type":"zip","url":"https://api.github.com/repos/php-http/guzzle6-adapter/zipball/459fa6e436cdc842bf3edf030dca7ecca9badec3","reference":"459fa6e436cdc842bf3edf030dca7ecca9badec3","shasum":""},"type":"library","time":"2016-01-13T11:53:07+00:00","autoload":{"psr-4":{"Http\\Adapter\\Guzzle6\\":"src/"}},"extra":{"branch-alias":{"dev-master":"0.5-dev"}},"require":{"php":">=5.5.0","php-http/httplug":"^1.0","guzzlehttp/guzzle":"^6.0"},"require-dev":{"ext-curl":"*","php-http/adapter-integration-tests":"^0.2"},"provide":{"php-http/client-implementation":"1.0","php-http/async-client-implementation":"1.0"},"uid":655617},"v1.0.0":{"name":"php-http/guzzle6-adapter","description":"Guzzle 6 HTTP Adapter","keywords":["http","Guzzle"],"homepage":"http://httplug.io","version":"v1.0.0","version_normalized":"1.0.0.0","license":["MIT"],"authors":[{"name":"Márk Sági-Kazár","email":"mark.sagikazar@gmail.com"},{"name":"David de Boer","email":"david@ddeboer.nl"}],"source":{"type":"git","url":"https://github.com/php-http/guzzle6-adapter.git","reference":"e884cf6dae5235fffd2a07f761e0066b9ebef170"},"dist":{"type":"zip","url":"https://api.github.com/repos/php-http/guzzle6-adapter/zipball/e884cf6dae5235fffd2a07f761e0066b9ebef170","reference":"e884cf6dae5235fffd2a07f761e0066b9ebef170","shasum":""},"type":"library","time":"2016-01-26T20:39:00+00:00","autoload":{"psr-4":{"Http\\Adapter\\Guzzle6\\":"src/"}},"extra":{"branch-alias":{"dev-master":"1.1-dev"}},"require":{"php":">=5.5.0","php-http/httplug":"^1.0","guzzlehttp/guzzle":"^6.0"},"require-dev":{"ext-curl":"*","php-http/adapter-integration-tests":"^0.3"},"provide":{"php-http/client-implementation":"1.0","php-http/async-client-implementation":"1.0"},"uid":673295},"v1.1.0":{"name":"php-http/guzzle6-adapter","description":"Guzzle 6 HTTP Adapter","keywords":["http","Guzzle"],"homepage":"http://httplug.io","version":"v1.1.0","version_normalized":"1.1.0.0","license":["MIT"],"authors":[{"name":"Márk Sági-Kazár","email":"mark.sagikazar@gmail.com"},{"name":"David de Boer","email":"david@ddeboer.nl"}],"source":{"type":"git","url":"https://github.com/php-http/guzzle6-adapter.git","reference":"c7a1c6b47530d88b7cb10949779505e2dbd8e7b4"},"dist":{"type":"zip","url":"https://api.github.com/repos/php-http/guzzle6-adapter/zipball/c7a1c6b47530d88b7cb10949779505e2dbd8e7b4","reference":"c7a1c6b47530d88b7cb10949779505e2dbd8e7b4","shasum":""},"type":"library","time":"2016-05-09T21:46:08+00:00","autoload":{"psr-4":{"Http\\Adapter\\Guzzle6\\":"src/"}},"extra":{"branch-alias":{"dev-master":"1.2-dev"}},"require":{"php":">=5.5.0","php-http/httplug":"^1.0","guzzlehttp/guzzle":"^6.0"},"require-dev":{"ext-curl":"*","php-http/adapter-integration-tests":"^0.4"},"provide":{"php-http/client-implementation":"1.0","php-http/async-client-implementation":"1.0"},"uid":813088},"v1.1.1":{"name":"php-http/guzzle6-adapter","description":"Guzzle 6 HTTP Adapter","keywords":["http","Guzzle"],"homepage":"http://httplug.io","version":"v1.1.1","version_normalized":"1.1.1.0","license":["MIT"],"authors":[{"name":"Márk Sági-Kazár","email":"mark.sagikazar@gmail.com"},{"name":"David de Boer","email":"david@ddeboer.nl"}],"source":{"type":"git","url":"https://github.com/php-http/guzzle6-adapter.git","reference":"a56941f9dc6110409cfcddc91546ee97039277ab"},"dist":{"type":"zip","url":"https://api.github.com/repos/php-http/guzzle6-adapter/zipball/a56941f9dc6110409cfcddc91546ee97039277ab","reference":"a56941f9dc6110409cfcddc91546ee97039277ab","shasum":""},"type":"library","time":"2016-05-10T06:13:32+00:00","autoload":{"psr-4":{"Http\\Adapter\\Guzzle6\\":"src/"}},"extra":{"branch-alias":{"dev-master":"1.2-dev"}},"require":{"php":">=5.5.0","php-http/httplug":"^1.0","guzzlehttp/guzzle":"^6.0"},"require-dev":{"ext-curl":"*","php-http/adapter-integration-tests":"^0.4"},"provide":{"php-http/client-implementation":"1.0","php-http/async-client-implementation":"1.0"},"uid":813415},"v2.0.0":{"name":"php-http/guzzle6-adapter","description":"Guzzle 6 HTTP Adapter","keywords":["http","Guzzle"],"homepage":"http://httplug.io","version":"v2.0.0","version_normalized":"2.0.0.0","license":["MIT"],"authors":[{"name":"Márk Sági-Kazár","email":"mark.sagikazar@gmail.com"},{"name":"David de Boer","email":"david@ddeboer.nl"}],"source":{"type":"git","url":"https://github.com/php-http/guzzle6-adapter.git","reference":"1e170d98db60780e399bced9a368151401f11b4c"},"dist":{"type":"zip","url":"https://api.github.com/repos/php-http/guzzle6-adapter/zipball/1e170d98db60780e399bced9a368151401f11b4c","reference":"1e170d98db60780e399bced9a368151401f11b4c","shasum":""},"type":"library","time":"2018-11-14T09:52:08+00:00","autoload":{"psr-4":{"Http\\Adapter\\Guzzle6\\":"src/"}},"extra":{"branch-alias":{"dev-master":"2.x-dev"}},"require":{"php":"^7.1","php-http/httplug":"^2.0","psr/http-client":"^1.0","guzzlehttp/guzzle":"^6.0"},"require-dev":{"ext-curl":"*","php-http/client-integration-tests":"^2.0"},"provide":{"php-http/client-implementation":"1.0","php-http/async-client-implementation":"1.0","psr/http-client-implementation":"1.0"},"uid":2578438},"v2.0.1":{"name":"php-http/guzzle6-adapter","description":"Guzzle 6 HTTP Adapter","keywords":["http","Guzzle"],"homepage":"http://httplug.io","version":"v2.0.1","version_normalized":"2.0.1.0","license":["MIT"],"authors":[{"name":"Márk Sági-Kazár","email":"mark.sagikazar@gmail.com"},{"name":"David de Boer","email":"david@ddeboer.nl"}],"source":{"type":"git","url":"https://github.com/php-http/guzzle6-adapter.git","reference":"6074a4b1f4d5c21061b70bab3b8ad484282fe31f"},"dist":{"type":"zip","url":"https://api.github.com/repos/php-http/guzzle6-adapter/zipball/6074a4b1f4d5c21061b70bab3b8ad484282fe31f","reference":"6074a4b1f4d5c21061b70bab3b8ad484282fe31f","shasum":""},"type":"library","time":"2018-12-16T14:44:03+00:00","autoload":{"psr-4":{"Http\\Adapter\\Guzzle6\\":"src/"}},"extra":{"branch-alias":{"dev-master":"2.x-dev"}},"require":{"php":"^7.1","php-http/httplug":"^2.0","psr/http-client":"^1.0","guzzlehttp/guzzle":"^6.0"},"require-dev":{"ext-curl":"*","phpunit/phpunit":"^7.4","php-http/client-integration-tests":"^2.0"},"provide":{"php-http/client-implementation":"1.0","php-http/async-client-implementation":"1.0","psr/http-client-implementation":"1.0"},"uid":2642067}}}}